django_favs_sc-0.2.5.dist-info/DESCRIPTION.rst
django_favs_sc-0.2.5.dist-info/METADATA
django_favs_sc-0.2.5.dist-info/metadata.json
django_favs_sc-0.2.5.dist-info/RECORD
django_favs_sc-0.2.5.dist-info/top_level.txt
django_favs_sc-0.2.5.dist-info/WHEEL
favit/__init__.py
favit/admin.py
favit/managers.py
favit/models.py
favit/urls.py
favit/views.py
favit/static/favit/css/favorite.css
favit/static/favit/css/css/favorite.css
favit/static/favit/js/favorite.js
favit/templates/favit/button.html
favit/templates/favit/unfave-button.html
favit/templatetags/__init__.py
favit/templatetags/favit_tags.py
