Metadata-Version: 2.0
Name: django-favs-sc
Version: 0.2.5
Summary: A simple reusable app for django that makes it easy to deal with faving
Home-page: https://github.com/SpencerCooley/django-favit
Author: Spencer Cooley
Author-email: contact@spencercooley.com
License: MIT License
Platform: UNKNOWN
Classifier: Environment :: Web Environment
Classifier: Framework :: Django
Classifier: Intended Audience :: Developers
Classifier: License :: OSI Approved :: MIT License
Classifier: Operating System :: OS Independent
Classifier: Programming Language :: Python
Classifier: Programming Language :: Python :: 2.6
Classifier: Programming Language :: Python :: 2.7
Classifier: Topic :: Internet :: WWW/HTTP
Classifier: Topic :: Internet :: WWW/HTTP :: Dynamic Content
Requires-Dist: simplejson
